healthcare_puller/__init__.py
healthcare_puller/federal_register/__init__.py
healthcare_puller/federal_register/cms_pullers.py
healthcare_puller/michigan_legislature/bill_and_analysis_puller.py
healthcare_puller-0.2.3.dist-info/METADATA
healthcare_puller-0.2.3.dist-info/WHEEL
healthcare_puller-0.2.3.dist-info/RECORD
